flask_zipkin.py
Anna_Flask_Zipkin-0.0.6.dist-info/METADATA
Anna_Flask_Zipkin-0.0.6.dist-info/WHEEL
Anna_Flask_Zipkin-0.0.6.dist-info/top_level.txt
Anna_Flask_Zipkin-0.0.6.dist-info/RECORD
