Metadata-Version: 2.1
Name: Anna-Flask-Zipkin
Version: 0.0.6
Summary: An zipkin extension for Flask based on py_zipkin.
Home-page: https://github.com/hyperanna01/anna-flask-zipkin
Author: Hyper Anna
Author-email: anna@hyperanna.com
License: BSD
Platform: any
Requires-Dist: Flask
Requires-Dist: py-zipkin (>=0.4.0)
Requires-Dist: requests (>=2.11.1)
